{
  "divisions": [
    {
      "id": "d1",
      "name": "School Effectiveness Division"
    },
    {
      "id": "d2",
      "name": "Employee Welfare Division"
    },
    {
      "id": "d3",
      "name": "Organization Effectiveness Division"
    },
    {
      "id": "d4",
      "name": "Personnel Division"
    },
    {
      "id": "1877c072-c1cb-4498-8f1c-6e1bb33ef641",
      "name": "Human Resource and Organizational Development Division"
    },
    {
      "id": "855a53c7-8c2d-4e58-ba45-8cc790bf179d",
      "name": "Education and Facilities Division"
    }
  ],
  "users": [
    {
      "id": "HRODI-E0008",
      "first_name": "Sebastian",
      "middle_name": "Omapas",
      "last_name": "Cheng",
      "division_id": "d1",
      "position": "Project Development Officer II",
      "hourly_rate": 50
    },
    {
      "id": "HRODI-E0009",
      "first_name": "Clea",
      "middle_name": "",
      "last_name": "Sacriz",
      "division_id": "d1",
      "position": "Technical Assistant I",
      "hourly_rate": 50
    },
    {
      "id": "HRODI-E0010",
      "first_name": "Klein",
      "middle_name": "",
      "last_name": "Catapang",
      "division_id": "d1",
      "position": "Technical Assistant I",
      "hourly_rate": 50
    },
    {
      "id": "HRODI-E0011",
      "first_name": "Marian",
      "middle_name": "",
      "last_name": "Efondo",
      "division_id": "d1",
      "position": "Project Development Officer IV",
      "hourly_rate": 50
    },
    {
      "id": "HRODI-E0012",
      "first_name": "TestUser_1771309100649",
      "middle_name": "",
      "last_name": "SyncCheck",
      "division_id": "d1",
      "position": "Tester",
      "hourly_rate": 50
    },
    {
      "id": "HRODI-E0013",
      "first_name": "TestUser_1771309100649",
      "middle_name": "",
      "last_name": "SyncCheck",
      "division_id": "d1",
      "position": "Tester",
      "hourly_rate": 50
    },
    {
      "id": "HRODI-E0014",
      "first_name": "Ina Marie Claire",
      "middle_name": "",
      "last_name": "Mallari",
      "division_id": "d1",
      "position": "Project Development Officer II",
      "hourly_rate": 50
    },
    {
      "id": "HRODI-E0015",
      "first_name": "Ina Marie Claire",
      "middle_name": "",
      "last_name": "Mallari",
      "division_id": "d1",
      "position": "Project Development Officer II",
      "hourly_rate": 50
    },
    {
      "id": "HRODI-E0002",
      "first_name": "Noverose ",
      "middle_name": "",
      "last_name": "Dadole",
      "division_id": "d1",
      "division": "School Effectiveness Division",
      "position": "Project Development Officer II"
    }
  ],
  "projects": [
    {
      "id": "HROD-P2098",
      "name": "National Learning Camp 2026",
      "description": "Implementation of learning recovery camps across all regions.",
      "division": "Human Resource and Organizational Development Division",
      "lead_personnel": "Sebastian Cheng",
      "supervising_officer": "Clea Sacriz",
      "assisting_personnel": "Staff A, Staff B",
      "status": "Ongoing",
      "total_budget": 2755571.9307804927,
      "basecamp_target": "Career Progression for DepEd Personnel, Workforce Plan and Management",
      "created_at": "2026-02-18T03:51:18.598Z"
    },
    {
      "id": "HROD-P6259",
      "name": "DepEd Digi-Transformation",
      "description": "Upgrading digital infrastructure and learning management systems.",
      "division": "Employee Welfare Division",
      "lead_personnel": "Sebastian Cheng",
      "supervising_officer": "Clea Sacriz",
      "assisting_personnel": "Staff A, Staff B",
      "status": "Ongoing",
      "total_budget": 3515442.565175254,
      "basecamp_target": "HROD Process Excellence",
      "created_at": "2026-02-18T03:51:19.182Z"
    },
    {
      "id": "HROD-P7210",
      "name": "Teacher Upskilling Program",
      "description": "Professional development series for K-12 educators.",
      "division": "Education and Facilities Division",
      "lead_personnel": "Sebastian Cheng",
      "supervising_officer": "Clea Sacriz",
      "assisting_personnel": "Staff A, Staff B",
      "status": "Ongoing",
      "total_budget": 3855648.277934468,
      "basecamp_target": "Career Opportunities in DepEd for SHS Graduates",
      "created_at": "2026-02-18T03:51:19.874Z"
    },
    {
      "id": "HRODI-P001",
      "name": "STRIDE Dashboard",
      "description": "Strategic Resource",
      "division": "School Effectiveness Division",
      "lead_personnel": "Sebastian Omapas Cheng",
      "supervising_officer": "Marian Efondo",
      "assisting_personnel": "Klein Catapang, Clea Sacriz",
      "total_budget": 0,
      "basecamp_target": "HROD Process Excellence",
      "status": "Planning",
      "created_at": "2026-02-18T05:51:31.842Z"
    }
  ],
  "tasks": [
    {
      "id": "HROD-A31483",
      "project_id": "HROD-P2098",
      "title": "Activity 1 for National Learning Camp 2026",
      "objective": "To complete specific deliverables.",
      "status": "Done",
      "start_date": "2026-02-18",
      "due_date": "2026-03-20",
      "budget": 50000,
      "cost": 20000,
      "assignee_id": "HRODI-E0008",
      "path": "HROD-A31483",
      "created_at": "2026-02-18T03:51:18.728Z",
      "expenses": [],
      "subtasks": [],
      "version": 2
    },
    {
      "id": "HROD-A97404",
      "project_id": "HROD-P2098",
      "title": "Activity 2 for National Learning Camp 2026",
      "objective": "To complete specific deliverables.",
      "status": "Done",
      "start_date": "2026-02-18",
      "due_date": "2026-03-20",
      "budget": 50000,
      "cost": 20000,
      "assignee_id": "HRODI-E0008",
      "path": "HROD-A97404",
      "created_at": "2026-02-18T03:51:18.941Z"
    },
    {
      "id": "HROD-A84159",
      "project_id": "HROD-P2098",
      "title": "Activity 3 for National Learning Camp 2026",
      "objective": "To complete specific deliverables.",
      "status": "Todo",
      "start_date": "2026-02-18",
      "due_date": "2026-03-20",
      "budget": 50000,
      "cost": 20000,
      "assignee_id": "HRODI-E0008",
      "path": "HROD-A84159",
      "created_at": "2026-02-18T03:51:19.020Z"
    },
    {
      "id": "HROD-A97063",
      "project_id": "HROD-P2098",
      "title": "Activity 4 for National Learning Camp 2026",
      "objective": "To complete specific deliverables.",
      "status": "Done",
      "start_date": "2026-02-18",
      "due_date": "2026-03-20",
      "budget": 50000,
      "cost": 20000,
      "assignee_id": "HRODI-E0008",
      "path": "HROD-A97063",
      "created_at": "2026-02-18T03:51:19.100Z"
    },
    {
      "id": "HROD-A29056",
      "project_id": "HROD-P6259",
      "title": "Activity 1 for DepEd Digi-Transformation",
      "objective": "To complete specific deliverables.",
      "status": "Done",
      "start_date": "2026-02-18",
      "due_date": "2026-03-20",
      "budget": 50000,
      "cost": 20000,
      "assignee_id": "HRODI-E0008",
      "path": "HROD-A29056",
      "created_at": "2026-02-18T03:51:19.301Z"
    },
    {
      "id": "HROD-A69934",
      "project_id": "HROD-P6259",
      "title": "Activity 2 for DepEd Digi-Transformation",
      "objective": "To complete specific deliverables.",
      "status": "Deferred",
      "start_date": "2026-02-18",
      "due_date": "2026-03-20",
      "budget": 50000,
      "cost": 20000,
      "assignee_id": "HRODI-E0008",
      "path": "HROD-A69934",
      "created_at": "2026-02-18T03:51:19.510Z",
      "expenses": [],
      "subtasks": [],
      "version": 3
    },
    {
      "id": "HROD-A45842",
      "project_id": "HROD-P6259",
      "title": "Activity 3 for DepEd Digi-Transformation",
      "objective": "To complete specific deliverables.",
      "status": "Done",
      "start_date": "2026-02-18",
      "due_date": "2026-03-20",
      "budget": 50000,
      "cost": 20000,
      "assignee_id": "HRODI-E0008",
      "path": "HROD-A45842",
      "created_at": "2026-02-18T03:51:19.710Z"
    },
    {
      "id": "HROD-A55347",
      "project_id": "HROD-P6259",
      "title": "Activity 4 for DepEd Digi-Transformation",
      "objective": "To complete specific deliverables.",
      "status": "In Progress",
      "start_date": "2026-02-18",
      "due_date": "2026-03-20",
      "budget": 50000,
      "cost": 20000,
      "assignee_id": "HRODI-E0008",
      "path": "HROD-A55347",
      "created_at": "2026-02-18T03:51:19.792Z"
    },
    {
      "id": "HROD-A23173",
      "project_id": "HROD-P7210",
      "title": "Activity 1 for Teacher Upskilling Program",
      "objective": "To complete specific deliverables.",
      "status": "Delayed",
      "start_date": "2026-02-18",
      "due_date": "2026-03-20",
      "budget": 50000,
      "cost": 20000,
      "assignee_id": "HRODI-E0008",
      "path": "HROD-A23173",
      "created_at": "2026-02-18T03:51:19.995Z"
    },
    {
      "id": "HROD-A67451",
      "project_id": "HROD-P7210",
      "title": "Activity 2 for Teacher Upskilling Program",
      "objective": "To complete specific deliverables.",
      "status": "Done",
      "start_date": "2026-02-18",
      "due_date": "2026-03-20",
      "budget": 50000,
      "cost": 20000,
      "assignee_id": "HRODI-E0008",
      "path": "HROD-A67451",
      "created_at": "2026-02-18T03:51:20.336Z"
    },
    {
      "id": "HROD-A35360",
      "project_id": "HROD-P7210",
      "title": "Activity 3 for Teacher Upskilling Program",
      "objective": "To complete specific deliverables.",
      "status": "Todo",
      "start_date": "2026-02-18",
      "due_date": "2026-03-20",
      "budget": 50000,
      "cost": 20000,
      "assignee_id": "HRODI-E0008",
      "path": "HROD-A35360",
      "created_at": "2026-02-18T03:51:20.423Z"
    },
    {
      "id": "HRODI-A001",
      "project_id": "HRODI-P001",
      "path": "HRODI-A001",
      "title": "Creation of the Dashboard",
      "objective": "",
      "status": "Todo",
      "priority": "Medium",
      "estimated_hours": 0,
      "start_date": "",
      "due_date": "2026-02-26",
      "cost": 0,
      "budget": 10000,
      "expenses": [
        {
          "id": "1771396093538",
          "description": "Funds",
          "date": "2026-02-18",
          "amount": 1000
        }
      ],
      "subtasks": [],
      "version": 4
    }
  ],
  "time_logs": [],
  "progress_logs": [],
  "project_updates": [],
  "indicators": [
    {
      "id": "29e1d203-7458-4c2a-ac8f-569bfc0183fb",
      "project_id": "HRODI-P010",
      "indicator": "Test Indicator 1771312588563",
      "target": 100,
      "created_at": "2026-02-17T07:16:28.585Z"
    },
    {
      "id": "39d046d8-c9d0-4793-81d8-23bfa8ab8392",
      "project_id": "HRODI-P010",
      "indicator": "Test Indicator 1771314960114",
      "target": 100,
      "created_at": "2026-02-17T07:56:00.129Z"
    },
    {
      "id": "13ae6e52-12ca-4d3f-b286-af1005d88ea0",
      "project_id": "HRODI-P010",
      "indicator": "Test Indicator 1771314997078",
      "target": 100,
      "created_at": "2026-02-17T07:56:37.080Z"
    },
    {
      "id": "daa10a4b-e628-4d13-86cb-ecde6c7fe72a",
      "project_id": "HRODI-P010",
      "indicator": "Test Indicator 1771315018063",
      "target": 100,
      "created_at": "2026-02-17T07:56:58.065Z"
    },
    {
      "id": "66b21294-42cf-45e0-9cc6-9fed8a7be76c",
      "project_id": "HRODI-P010",
      "activity_id": "HRODI-A038",
      "indicator": "Test Indicator 1771315034624",
      "target": 100,
      "created_at": "2026-02-17T07:57:14.635Z"
    },
    {
      "id": "862667ba-df0a-4888-b98b-cede986c2360",
      "project_id": "HRODI-P010",
      "activity_id": "HRODI-A038",
      "indicator": "Data Analyzed ",
      "target": 344,
      "created_at": "2026-02-17T07:58:43.459Z"
    },
    {
      "id": "21fd36df-2c98-4d67-98c1-5a4d1e0534e8",
      "project_id": "HRODI-P010",
      "activity_id": "HRODI-A033",
      "indicator": "Schools Visited",
      "target": 23,
      "created_at": "2026-02-17T07:58:53.746Z"
    },
    {
      "id": "89c64f4c-dd1a-4f38-ae18-31efc332abf7",
      "project_id": "HRODI-P010",
      "activity_id": "HRODI-A038",
      "indicator": "Wala Lang",
      "target": 123,
      "created_at": "2026-02-17T08:03:25.300Z"
    },
    {
      "id": "af21e3c8-d194-41be-8a72-832be56908bb",
      "project_id": "HRODI-P010",
      "activity_id": "HRODI-A033",
      "indicator": "Hehehe",
      "target": 123,
      "created_at": "2026-02-17T08:08:29.737Z"
    },
    {
      "id": "8f8e115b-4fe3-4a29-bc7e-6b74c9551f62",
      "project_id": "HRODI-P010",
      "activity_id": "HRODI-A033",
      "indicator": "Helloasdfasdfas",
      "target": 123,
      "created_at": "2026-02-17T08:09:20.111Z"
    },
    {
      "id": "ad0eb1ac-ec2c-40cf-902d-ebb94ff61af6",
      "project_id": "HRODI-P010",
      "activity_id": "HRODI-A037",
      "indicator": "Ayun O",
      "target": 123,
      "created_at": "2026-02-17T08:10:41.530Z"
    },
    {
      "id": "846a42ee-e8a4-4fc4-b528-bbba67da8e18",
      "project_id": "HRODI-P001",
      "activity_id": "HRODI-A001",
      "indicator": "CC Ref Test 1771316170539",
      "target": 50,
      "created_at": "2026-02-17T08:16:10.553Z"
    },
    {
      "id": "ea23a3f7-efb6-42c3-b790-bdeed216de96",
      "project_id": "HRODI-P010",
      "activity_id": "HRODI-A037",
      "indicator": "Asdfasdfasd",
      "target": 321,
      "created_at": "2026-02-17T08:17:25.547Z"
    },
    {
      "id": "a9055590-7de6-4d58-99bf-39710b1f4964",
      "project_id": "HRODI-P010",
      "activity_id": "HRODI-A037",
      "indicator": "Testtest",
      "target": 123,
      "created_at": "2026-02-17T08:19:38.425Z"
    },
    {
      "id": "4a736edc-d901-4ce9-be49-ee488c11c47f",
      "project_id": "HRODI-P010",
      "activity_id": "HRODI-A038",
      "indicator": "Mlbb",
      "target": 123,
      "created_at": "2026-02-17T08:26:12.822Z"
    }
  ],
  "catchups": [
    {
      "id": "8a03dfc4-ac22-4d65-8420-1e2d11db3ede",
      "activity_id": "HROD-A69934",
      "title": "Catch-up for Activity 2",
      "description": "Expedited processing required",
      "target_date": "2026-03-05",
      "status": "Pending",
      "reason": "Unforeseen delays in procurement",
      "created_at": "2026-02-18T03:51:19.592Z"
    },
    {
      "id": "400a0cef-c177-4de5-a128-2536642d0fd2",
      "activity_id": "HROD-A23173",
      "title": "Catch-up for Activity 1",
      "description": "Expedited processing required",
      "target_date": "2026-03-05",
      "status": "Pending",
      "reason": "Unforeseen delays in procurement",
      "created_at": "2026-02-18T03:51:20.216Z"
    }
  ],
  "milestones": [
    {
      "id": "HROD-M83073",
      "project_id": "HROD-P2098",
      "title": "Kickoff for National Learning Camp 2026",
      "description": "Initial stakeholder meeting",
      "target_date": "2026-02-18",
      "status": "Accomplished",
      "notes": "Went well",
      "created_at": "2026-02-18T03:51:18.811Z",
      "importance": 4
    },
    {
      "id": "HROD-M45904",
      "project_id": "HROD-P6259",
      "title": "Kickoff for DepEd Digi-Transformation",
      "description": "Initial stakeholder meeting",
      "target_date": "2026-02-18",
      "status": "Accomplished",
      "notes": "Went well",
      "created_at": "2026-02-18T03:51:19.384Z",
      "importance": 5
    },
    {
      "id": "HROD-M62777",
      "project_id": "HROD-P7210",
      "title": "Kickoff for Teacher Upskilling Program",
      "description": "Initial stakeholder meeting",
      "target_date": "2026-02-18",
      "status": "Accomplished",
      "notes": "Went well",
      "created_at": "2026-02-18T03:51:20.082Z",
      "importance": 3
    },
    {
      "id": "HRODI-M0001",
      "project_id": "HROD-P6259",
      "title": "LAKSDFKLANS",
      "description": "ALSDKNFL",
      "target_date": "2026-08-19",
      "status": "Pending",
      "notes": "HJHIU",
      "created_at": "2026-02-18T04:04:17.199Z",
      "importance": 2
    },
    {
      "id": "HRODI-M0002",
      "project_id": "HRODI-P001",
      "title": "Created the Dashboard",
      "description": "",
      "target_date": "2026-02-02",
      "status": "Accomplished",
      "notes": "",
      "importance": 4,
      "created_at": "2026-02-18T05:52:01.702Z"
    }
  ]
}